devicecheck/__init__.py
devicecheck/asyncio.py
devicecheck/decorators.py
devicecheck-1.3.3.dist-info/LICENSE
devicecheck-1.3.3.dist-info/METADATA
devicecheck-1.3.3.dist-info/WHEEL
devicecheck-1.3.3.dist-info/top_level.txt
devicecheck-1.3.3.dist-info/RECORD
