Metadata-Version: 2.1
Name: devicecheck
Version: 1.3.3
Summary: Apple DeviceCheck API. Reduce fraudulent use of your services by managing device state and asserting app integrity.
Home-page: https://github.com/Kylmakalle/devicecheck
Author: Sergey Akentev
Author-email: "S. Akentev" <sergey+gh@akentev.com>
Project-URL: Issue Tracker, https://github.com/Kylmakalle/devicecheck/issues
Project-URL: Repository, https://github.com/Kylmakalle/devicecheck
Classifier: Programming Language :: Python :: 3
Classifier: License :: OSI Approved :: MIT License
Classifier: Operating System :: OS Independent
Requires-Python: >=3.6
License-File: LICENSE
Requires-Dist: requests >=2.20.0
Requires-Dist: pyjwt >=2.8.0
Requires-Dist: cryptography >=3.4.7
Provides-Extra: async
Requires-Dist: aiohttp >=3.8 ; extra == 'async'
